.gitignore
LICENSE.txt
README
setup.py
django_tokyo_sessions.egg-info/PKG-INFO
django_tokyo_sessions.egg-info/SOURCES.txt
django_tokyo_sessions.egg-info/dependency_links.txt
django_tokyo_sessions.egg-info/not-zip-safe
django_tokyo_sessions.egg-info/requires.txt
django_tokyo_sessions.egg-info/top_level.txt
tokyo_sessions/__init__.py
tokyo_sessions/settings.py
tokyo_sessions/tests.py
tokyo_sessions/tokyo.py