Metadata-Version: 1.0
Name: django-tokyo-sessions
Version: 0.1.0
Summary: This is a session backend for Django that stores sessions in a Tokyo Cabinet database, which communicates via Tokyo Tyrant using the PyTyrant library.  Tokyo Cabinet is a key-value store similar to BDB.
Home-page: http://github.com/ericflo/django-tokyo-sessions/tree/master
Author: Eric Florenzano
Author-email: floguy@gmail.com
License: BSD
Keywords: tokyo,session,cabinet,tyrant,pytyrant,django
Platform: UNKNOWN
Classifier: Programming Language :: Python
Classifier: Topic :: Software Development :: Libraries :: Python Modules
Classifier: Framework :: Django
Classifier: Environment :: Web Environment
